Metadata-Version: 2.1
Name: odoo12-addon-website-sale-product-detail-attribute-value-image
Version: 12.0.1.1.0
Summary: Display attributes values images in shop product detail
Home-page: https://github.com/OCA/e-commerce
Author: Tecnativa, Odoo Community Association (OCA)
Author-email: support@odoo-community.org
License: AGPL-3
Platform: UNKNOWN
Classifier: Programming Language :: Python
Classifier: Framework :: Odoo
Classifier: License :: OSI Approved :: GNU Affero General Public License v3
Classifier: Development Status :: 4 - Beta
Requires-Python: >=3.5
Requires-Dist: odoo (<12.1dev,>=12.0a)
